linmult/__init__.py
linmult/models/LinMulT.py
linmult/models/LinT.py
linmult/models/__init__.py
linmult/models/attention.py
linmult/models/heads.py
linmult/models/modules.py
linmult/models/positional_embedding.py
linmult/models/transformer.py
linmult/models/utils.py
linmult/test/__init__.py
linmult/test/test_architecture.py
linmult/test/test_attention.py
linmult/test/test_inputs.py
linmult/test/test_mask.py
linmult-1.8.1.dist-info/METADATA
linmult-1.8.1.dist-info/WHEEL
linmult-1.8.1.dist-info/licenses/LICENSE
linmult-1.8.1.dist-info/RECORD
