Metadata-Version: 2.4
Name: linmult
Version: 1.8.1
Summary: General-purpose Multimodal Transformer with Linear Complexity Attention Mechanism.
Project-URL: Documentation, https://github.com/fodorad/linmult#readme
Project-URL: Issues, https://github.com/fodorad/linmult/issues
Project-URL: Source, https://github.com/fodorad/linmult
Author-email: fodorad <foauaai@inf.elte.hu>
License-File: LICENSE
Keywords: linear-complexity attention,multimodal,transformer
Classifier: Operating System :: OS Independent
Classifier: Programming Language :: Python :: 3
Requires-Python: >=3.11
Requires-Dist: pyyaml
Requires-Dist: torch==2.5.1
